scumprogrammer/InterfaceCli.py
scumprogrammer/InterfaceWeb.py
scumprogrammer/OpenHdlc.py
scumprogrammer/ScumConnector.py
scumprogrammer/ScumUtils.py
scumprogrammer/VERSION.py
scumprogrammer/__init__.py
scumprogrammer/__main__.py
scumprogrammer/static/d3.min.js
scumprogrammer/static/jquery-3.6.0.min.js
scumprogrammer/static/scum.css
scumprogrammer/static/scum.js
scumprogrammer/views/index.tpl
scumprogrammer-0.0.6.dist-info/METADATA
scumprogrammer-0.0.6.dist-info/WHEEL
scumprogrammer-0.0.6.dist-info/entry_points.txt
scumprogrammer-0.0.6.dist-info/top_level.txt
scumprogrammer-0.0.6.dist-info/RECORD
