Metadata-Version: 2.1
Name: scumprogrammer
Version: 0.0.6
Summary: Program and interact with your SCuM chip
Home-page: http://www.crystalfree.org/
Author: Thomas Watteyne
Author-email: twatteyne@gmail.com
License: UNKNOWN
Project-URL: Source Code, https://github.com/openwsn-berkeley/SCuM-programmer/
Project-URL: Bug Tracker, https://github.com/openwsn-berkeley/SCuM-programmer/issues
Platform: UNKNOWN
Classifier: Programming Language :: Python :: 3
Classifier: License :: OSI Approved :: BSD License
Classifier: Operating System :: OS Independent
Requires-Dist: pyserial
Requires-Dist: bottle
